{"duration": 25.025524854660034, "input_args": {"imgs": "'/nfshome/sandbox/perceptron/cobre/fmri_0040052.nii.gz'", "extraction_function": "<nilearn.input_data.nifti_maps_masker._ExtractionFunctor object at 0x7f224287c828>", "parameters": "{'allow_overlap': True, 'detrend': True, 'dtype': None, 'high_pass': 0.01, 'low_pass': 0.5, 'maps_img': '/nfshome/sandbox/msdl_atlas/MSDL_rois/msdl_rois.nii', 'mask_img': None, 'smoothing_fwhm': None, 'standardize': True, 't_r': 2.0, 'target_shape': (40, 48, 35), 'target_affine': array([[   4.,    0.,    0.,  -78.],\n       [   0.,    4.,    0., -111.],\n       [   0.,    0.,    4.,  -51.],\n       [   0.,    0.,    0.,    1.]])}", "confounds": "[array([[-0.04129305,  0.00325315,  0.01895836, ...,  0.02459814,\n         0.23593242, -0.21593903],\n       [-0.04073876,  0.00611772,  0.02544717, ...,  0.05140083,\n         0.16160107,  0.00862083],\n       [-0.02509955,  0.0186262 ,  0.03476897, ...,  0.01421393,\n         0.12543789,  0.08536787],\n       ...,\n       [-0.03548533,  0.03859292,  0.15404391, ..., -0.13597967,\n         0.04338593,  0.0708392 ],\n       [ 0.00893823,  0.00141615,  0.12125833, ..., -0.11433181,\n        -0.05322181,  0.03885074],\n       [-0.01627581, -0.08828173,  0.09902552, ..., -0.04512472,\n        -0.02764382,  0.07293452]], dtype=float32), '/nfshome/sandbox/perceptron/cobre/fmri_0040052.tsv']", "copy": "True", "dtype": "None"}}