{"duration": 30.381656169891357, "input_args": {"imgs": "'/nfshome/sandbox/perceptron/cobre/fmri_0040039.nii.gz'", "extraction_function": "<nilearn.input_data.nifti_maps_masker._ExtractionFunctor object at 0x7f2292c61a90>", "parameters": "{'allow_overlap': True, 'detrend': True, 'dtype': None, 'high_pass': 0.01, 'low_pass': 0.5, 'maps_img': '/nfshome/sandbox/msdl_atlas/MSDL_rois/msdl_rois.nii', 'mask_img': None, 'smoothing_fwhm': None, 'standardize': True, 't_r': 2.0, 'target_shape': (40, 48, 35), 'target_affine': array([[   4.,    0.,    0.,  -78.],\n       [   0.,    4.,    0., -111.],\n       [   0.,    0.,    4.,  -51.],\n       [   0.,    0.,    0.,    1.]])}", "confounds": "[array([[-0.16116552, -0.2128461 ,  0.01999237, ..., -0.145137  ,\n        -0.01823338, -0.17780173],\n       [-0.15365821, -0.1810467 ,  0.04479592, ..., -0.05861641,\n        -0.02409376, -0.08185868],\n       [-0.15311685, -0.15976748, -0.02469302, ...,  0.03233676,\n        -0.00662877, -0.01259181],\n       ...,\n       [-0.15897588,  0.06491177,  0.0670331 , ...,  0.02758966,\n        -0.0405171 ,  0.21941538],\n       [-0.12596473,  0.04286025,  0.14161909, ..., -0.04164242,\n        -0.13064322,  0.10116493],\n       [-0.16568461,  0.06294036,  0.04320744, ...,  0.02525631,\n        -0.02437982,  0.17012076]], dtype=float32), '/nfshome/sandbox/perceptron/cobre/fmri_0040039.tsv']", "copy": "True", "dtype": "None"}}