{"duration": 22.923346996307373, "input_args": {"imgs": "'/nfshome/sandbox/perceptron/cobre/fmri_0040029.nii.gz'", "extraction_function": "<nilearn.input_data.nifti_maps_masker._ExtractionFunctor object at 0x7f21b8bbaf98>", "parameters": "{'allow_overlap': True, 'detrend': True, 'dtype': None, 'high_pass': 0.01, 'low_pass': 0.5, 'maps_img': '/nfshome/sandbox/msdl_atlas/MSDL_rois/msdl_rois.nii', 'mask_img': None, 'smoothing_fwhm': None, 'standardize': True, 't_r': 2.0, 'target_shape': (40, 48, 35), 'target_affine': array([[   4.,    0.,    0.,  -78.],\n       [   0.,    4.,    0., -111.],\n       [   0.,    0.,    4.,  -51.],\n       [   0.,    0.,    0.,    1.]])}", "confounds": "[array([[ 0.07352922, -0.23785491,  0.10802651, ...,  0.25985718,\n        -0.22939134, -0.25401253],\n       [ 0.23691219, -0.21629035,  0.0967623 , ...,  0.16999713,\n         0.04147469, -0.0434339 ],\n       [ 0.02208796, -0.17239594,  0.21843512, ...,  0.10803563,\n        -0.11539931, -0.07381324],\n       ...,\n       [-0.05576097, -0.11343484,  0.18278894, ...,  0.00603948,\n         0.18311633,  0.03984331],\n       [-0.06088628, -0.11869153,  0.1898524 , ..., -0.08048206,\n         0.13816045,  0.04419422],\n       [-0.04680852, -0.11708702,  0.18044904, ..., -0.14211455,\n         0.11097513,  0.11790581]], dtype=float32), '/nfshome/sandbox/perceptron/cobre/fmri_0040029.tsv']", "copy": "True", "dtype": "None"}}