{"duration": 20.51374912261963, "input_args": {"imgs": "'/nfshome/sandbox/perceptron/cobre/fmri_0040095.nii.gz'", "extraction_function": "<nilearn.input_data.nifti_maps_masker._ExtractionFunctor object at 0x7f21b8bbaf98>", "parameters": "{'allow_overlap': True, 'detrend': True, 'dtype': None, 'high_pass': 0.01, 'low_pass': 0.5, 'maps_img': '/nfshome/sandbox/msdl_atlas/MSDL_rois/msdl_rois.nii', 'mask_img': None, 'smoothing_fwhm': None, 'standardize': True, 't_r': 2.0, 'target_shape': (40, 48, 35), 'target_affine': array([[   4.,    0.,    0.,  -78.],\n       [   0.,    4.,    0., -111.],\n       [   0.,    0.,    4.,  -51.],\n       [   0.,    0.,    0.,    1.]])}", "confounds": "[array([[-0.00963749, -0.1341896 ,  0.18793547, ..., -0.00851735,\n         0.1512132 , -0.20887806],\n       [-0.00678803, -0.08458459, -0.02700967, ..., -0.10152694,\n         0.05178422, -0.04413184],\n       [-0.03902808, -0.16799937,  0.10734864, ..., -0.06410499,\n         0.10128405,  0.13592264],\n       ...,\n       [-0.11887044, -0.07182376,  0.04537124, ...,  0.06800143,\n        -0.03477495,  0.03421601],\n       [-0.01854986, -0.06769492, -0.05799339, ...,  0.03529911,\n         0.08008286,  0.01014511],\n       [-0.09321804, -0.07624193,  0.103954  , ...,  0.07664874,\n         0.11904189, -0.16027737]], dtype=float32), '/nfshome/sandbox/perceptron/cobre/fmri_0040095.tsv']", "copy": "True", "dtype": "None"}}